wbparser/__init__.py
wbparser/main.py
wbparser/wildberries/__init__.py
wbparser/wildberries/wildberries/__init__.py
wbparser/wildberries/wildberries/items.py
wbparser/wildberries/wildberries/middlewares.py
wbparser/wildberries/wildberries/pipelines.py
wbparser/wildberries/wildberries/settings.py
wbparser/wildberries/wildberries/spiders/__init__.py
wbparser/wildberries/wildberries/spiders/goods.py
wbparser/wildberries/wildberries/spiders/sitemap.py
wbparser-0.2.0.dist-info/LICENSE
wbparser-0.2.0.dist-info/METADATA
wbparser-0.2.0.dist-info/WHEEL
wbparser-0.2.0.dist-info/top_level.txt
wbparser-0.2.0.dist-info/RECORD
