Metadata-Version: 2.1
Name: wbparser
Version: 0.2.0
Summary: WB parser (async)
Home-page: https://github.com/maxim-lixakov/WildBerriesParser
Author: Maxim Liksakov
Author-email: lixakov.maksim@yandex.ru
License: MIT
Classifier: Development Status :: 3 - Alpha
Classifier: Intended Audience :: Developers
Classifier: License :: OSI Approved :: MIT License
Classifier: Programming Language :: Python :: 3
Classifier: Programming Language :: Python :: 3.6
Classifier: Programming Language :: Python :: 3.7
Classifier: Programming Language :: Python :: 3.8
Classifier: Programming Language :: Python :: 3.9
License-File: LICENSE
Requires-Dist: scrapy
